pythonodejs.cpython-312-x86_64-linux-gnu.so
pythonodejs/__init__.py
pythonodejs/main.py
pythonodejs/lib/libnode.so
pythonodejs/lib/libnode.so.131
pythonodejs/lib/node
pythonodejs/lib/pythonodejs.so
pythonodejs-1.4.5.dist-info/METADATA
pythonodejs-1.4.5.dist-info/WHEEL
pythonodejs-1.4.5.dist-info/top_level.txt
pythonodejs-1.4.5.dist-info/RECORD
pythonodejs-1.4.5.dist-info/licenses/LICENSE
