Metadata-Version: 2.4
Name: pythonodejs
Version: 1.4.5
Summary: Embed Node.js natively in your Python code.
Author: 0880880
License: Copyright 2025 0880880
License-File: LICENSE
Dynamic: license-file
